[{"compId": 12,"delegAlias": "Monopoly","delegUniversity": "Polytechnique","teamScore": 95.37953795},
  {"compId": 12,"delegAlias": "Rouge","delegUniversity": "Universit\u00e9 Laval","teamScore": 37.95379538},
  {"compId": 12,"delegAlias": "Azulus","delegUniversity": "Universit\u00e9 de Sherbrooke","teamScore": 0},
  {"compId": 12,"delegAlias": "Or","delegUniversity": "Universit\u00e9 Laval","teamScore": 48.84488449},
  {"compId": 12,"delegAlias": "Red Team","delegUniversity": "Concordia University","teamScore": 60.72607261},
  {"compId": 12,"delegAlias": "Rubius","delegUniversity": "Universit\u00e9 de Sherbrooke","teamScore": 42.24422442},
  {"compId": 12,"delegAlias": "PoETS","delegUniversity": "\u00c9cole de technologie sup\u00e9rieure","teamScore": 57.09570957},
  {"compId": 12,"delegAlias": "Bricked up","delegUniversity": "Universit\u00e9 de Montr\u00e9al","teamScore": 86.46864686},
  {"compId": 12,"delegAlias": "I eat bricks","delegUniversity": "University of Windsor","teamScore": 91.41914191},
  {"compId": 12,"delegAlias": "Duopoly","delegUniversity": "Polytechnique","teamScore": 58.41584158},
  {"compId": 12,"delegAlias": "404 Brick not found","delegUniversity": "Universit\u00e9 de Montr\u00e9al","teamScore": 64.35643564},
  {"compId": 12,"delegAlias": "/greve/null","delegUniversity": "Universit\u00e9 du Qu\u00e9bec \u00e0 Montr\u00e9al","teamScore": 76.23762376},
  {"compId": 12,"delegAlias": "McDrill","delegUniversity": "Mcgill University","teamScore": 5.940594059},
  {"compId": 12,"delegAlias": "uOttaCommit","delegUniversity": "Universitty of Ottawa","teamScore": 41.58415842},
  {"compId": 12,"delegAlias": "Blue Team","delegUniversity": "Concordia University","teamScore": 23.10231023},
  {"compId": 12,"delegAlias": "null pointer brickception","delegUniversity": "University of Windsor","teamScore": 100},
  {"compId": 12,"delegAlias": "/dev/greve","delegUniversity": "Universit\u00e9 du Qu\u00e9bec \u00e0 Montr\u00e9al","teamScore": 18.48184818},
  {"compId": 12,"delegAlias": "ArchiETS","delegUniversity": "\u00c9cole de technologie sup\u00e9rieure","teamScore": 38.94389439},
  {"compId": 12,"delegAlias": "New builders","delegUniversity": "Universit\u00e9 du Qu\u00e9bec \u00e0 Chicoutimi","teamScore": 23.43234323},
  {"compId": 12,"delegAlias": "Chum Bucket","delegUniversity": "Universit\u00e9 du Qu\u00e9bec en Outaouais","teamScore": 0},
  {"compId": 12,"delegAlias": "Krusty Krab","delegUniversity": "Universit\u00e9 du Qu\u00e9bec en Outaouais","teamScore": 0},
  {"compId": 12,"delegAlias": "ITR","delegUniversity": "ITR","teamScore": 0}]