[{"compId": 13,"delegAlias": "Monopoly","delegUniversity": "Polytechnique","teamScore": 38.20366599},
  {"compId": 13,"delegAlias": "Rouge","delegUniversity": "Universit\u00e9 Laval","teamScore": 55.9898167},
  {"compId": 13,"delegAlias": "Azulus","delegUniversity": "Universit\u00e9 de Sherbrooke","teamScore": 90.83503055},
  {"compId": 13,"delegAlias": "Or","delegUniversity": "Universit\u00e9 Laval","teamScore": 82.12830957},
  {"compId": 13,"delegAlias": "Red Team","delegUniversity": "Concordia University","teamScore": 61.15885947},
  {"compId": 13,"delegAlias": "Rubius","delegUniversity": "Universit\u00e9 de Sherbrooke","teamScore": 100},
  {"compId": 13,"delegAlias": "PoETS","delegUniversity": "\u00c9cole de technologie sup\u00e9rieure","teamScore": 74.88798371},
  {"compId": 13,"delegAlias": "Bricked up","delegUniversity": "Universit\u00e9 de Montr\u00e9al","teamScore": 0},
  {"compId": 13,"delegAlias": "I eat bricks","delegUniversity": "University of Windsor","teamScore": 65.88798371},
  {"compId": 13,"delegAlias": "Duopoly","delegUniversity": "Polytechnique","teamScore": 0},
  {"compId": 13,"delegAlias": "404 Brick not found","delegUniversity": "Universit\u00e9 de Montr\u00e9al","teamScore": 0},
  {"compId": 13,"delegAlias": "/greve/null","delegUniversity": "Universit\u00e9 du Qu\u00e9bec \u00e0 Montr\u00e9al","teamScore": 0},
  {"compId": 13,"delegAlias": "McDrill","delegUniversity": "Mcgill University","teamScore": 67.21995927},
  {"compId": 13,"delegAlias": "uOttaCommit","delegUniversity": "Universitty of Ottawa","teamScore": 0},
  {"compId": 13,"delegAlias": "Blue Team","delegUniversity": "Concordia University","teamScore": 25},
  {"compId": 13,"delegAlias": "null pointer brickception","delegUniversity": "University of Windsor","teamScore": 25},
  {"compId": 13,"delegAlias": "/dev/greve","delegUniversity": "Universit\u00e9 du Qu\u00e9bec \u00e0 Montr\u00e9al","teamScore": 0},
  {"compId": 13,"delegAlias": "ArchiETS","delegUniversity": "\u00c9cole de technologie sup\u00e9rieure","teamScore": 0},
  {"compId": 13,"delegAlias": "New builders","delegUniversity": "Universit\u00e9 du Qu\u00e9bec \u00e0 Chicoutimi","teamScore": 25},
  {"compId": 13,"delegAlias": "Chum Bucket","delegUniversity": "Universit\u00e9 du Qu\u00e9bec en Outaouais","teamScore": 25},
  {"compId": 13,"delegAlias": "Krusty Krab","delegUniversity": "Universit\u00e9 du Qu\u00e9bec en Outaouais","teamScore": 25},
  {"compId": 13,"delegAlias": "ITR","delegUniversity": "ITR","teamScore": 25}]