[{"delegID": 9, "delegUniversity": "Universit\u00c3\u00a9 Laval", "delegAlias": "28 Bugs Later", "compID": 13, "teamScore": 100.0}, {"delegID": 14, "delegUniversity": "\u00c3\u2030cole de technologie sup\u00c3\u00a9rieure", "delegAlias": "2038", "compID": 13, "teamScore": 90.0}, {"delegID": 17, "delegUniversity": "Universit\u00c3\u00a9 de Montr\u00c3\u00a9al", "delegAlias": "IRO", "compID": 13, "teamScore": 75.0}, {"delegID": 3, "delegUniversity": "\u00c3\u2030cole Polytechnique de Montr\u00c3\u00a9al", "delegAlias": "Mayan Cats of the Moon", "compID": 13, "teamScore": 66.25}, {"delegID": 35, "delegUniversity": "University of Guelph", "delegAlias": "Mad Cows of Guelph", "compID": 13, "teamScore": 57.49999999999999}, {"delegID": 10, "delegUniversity": "Universit\u00c3\u00a9 Laval", "delegAlias": "Skynet", "compID": 13, "teamScore": 55.00000000000001}, {"delegID": 12, "delegUniversity": "Universit\u00c3\u00a9 de Sherbrooke", "delegAlias": "Say No! to order 66", "compID": 13, "teamScore": 55.00000000000001}, {"delegID": 29, "delegUniversity": "University of Rochester", "delegAlias": "( ApocaLISP )", "compID": 13, "teamScore": 55.00000000000001}, {"delegID": 39, "delegUniversity": "Rochester Institute of Technology", "delegAlias": "Society of Software Engineers", "compID": 13, "teamScore": 53.75}, {"delegID": 11, "delegUniversity": "uOttawa", "delegAlias": "Citation Needed", "compID": 13, "teamScore": 52.5}, {"delegID": 33, "delegUniversity": "Concordia University", "delegAlias": "The Honey Badgers", "compID": 13, "teamScore": 48.75}, {"delegID": 34, "delegUniversity": "University of Manitoba", "delegAlias": "the \\&#039;);DROP TABLE\\&#039;s", "compID": 13, "teamScore": 42.5}, {"delegID": 2, "delegUniversity": "\u00c3\u2030cole Polytechnique de Montr\u00c3\u00a9al", "delegAlias": "Mayan Cats of the Sun", "compID": 13, "teamScore": 37.5}, {"delegID": 13, "delegUniversity": "\u00c3\u2030cole de technologie sup\u00c3\u00a9rieure", "delegAlias": "Twenty Dirty Apes", "compID": 13, "teamScore": 0.0}, {"delegID": 36, "delegUniversity": "University of Manitoba", "delegAlias": "umcs1", "compID": 13, "teamScore": 0.0}]